{"items": [{"topicName": "/driver/lidar/top/voxelized", "topicType": "sensor_msgs/PointCloud2", "viewer": "Multi3DViewer", "viewState": {"cam_theta": 2.965966666666668, "cam_phi": 0.49666666666666737, "cam_r": 44.9, "cam_offset_x": 0, "cam_offset_y": 0, "cam_offset_z": 0, "baseFrame": "map", "layers": [{"topic": "/map", "type": "nav_msgs/OccupancyGrid", "color": [1, 1, 1, 1], "size": 2.5, "visible": true, "baseFrame": "map", "occShowOccupied": true, "occShowFree": false, "occShowUnknown": false, "occOccupiedThreshold": 65, "occStride": 1, "pclDecimation": 1}, {"topic": "/robot_model", "type": "visualization_msgs/MarkerArray", "color": [1, 1, 1, 1], "size": 2.5, "visible": true, "baseFrame": "map", "occShowOccupied": true, "occShowFree": false, "occShowUnknown": false, "occOccupiedThreshold": 65, "occStride": 1, "pclDecimation": 1}, {"topic": "/localization/current_pose", "type": "geometry_msgs/PoseStamped", "color": [1, 1, 1, 1], "size": 2.5, "visible": true, "baseFrame": "map", "occShowOccupied": true, "occShowFree": false, "occShowUnknown": false, "occOccupiedThreshold": 65, "occStride": 1, "pclDecimation": 1}, {"topic": "/move_base/PathPlanner/plan", "type": "nav_msgs/Path", "color": [1, 1, 1, 1], "size": 2.5, "visible": true, "baseFrame": "map", "occShowOccupied": true, "occShowFree": false, "occShowUnknown": false, "occOccupiedThreshold": 65, "occStride": 1, "pclDecimation": 1}, {"topic": "/robox_goal", "type": "geometry_msgs/PoseStamped", "color": [1, 1, 1, 1], "size": 2.5, "visible": true, "baseFrame": "map", "occShowOccupied": true, "occShowFree": false, "occShowUnknown": false, "occOccupiedThreshold": 65, "occStride": 1, "pclDecimation": 1}, {"topic": "/localization/cloud_in_map", "type": "sensor_msgs/PointCloud2", "color": [1, 1, 1, 1], "size": 2.5, "visible": true, "baseFrame": "map", "occShowOccupied": true, "occShowFree": false, "occShowUnknown": false, "occOccupiedThreshold": 65, "occStride": 1, "pclDecimation": 1}], "pcdLayers": []}, "width": 396.78125, "height": 1389.109375, "isManualControl": false, "isTopicsMonitor": false, "isControlActivator": false}]}